README.md
burpextender_pb2.py
burpextender_pb2_grpc.py
pyburp.py
setup.py
pyburp.egg-info/PKG-INFO
pyburp.egg-info/SOURCES.txt
pyburp.egg-info/dependency_links.txt
pyburp.egg-info/requires.txt
pyburp.egg-info/top_level.txt