Metadata-Version: 2.1
Name: pyburp
Version: 1.0.1
Summary: The rpc server api of https://github.com/cyal1/BcryptMontoya
Home-page: https://github.com/cyal1/pyburpRPC/tree/main/python
Author: cyal1
Author-email: admin@example.com
Requires-Python: >=3.9.9
